odoo/addons/product_list_price_from_pricelist/README.rst
odoo/addons/product_list_price_from_pricelist/__init__.py
odoo/addons/product_list_price_from_pricelist/__manifest__.py
odoo/addons/product_list_price_from_pricelist/data/cron.xml
odoo/addons/product_list_price_from_pricelist/i18n/es.po
odoo/addons/product_list_price_from_pricelist/i18n/it.po
odoo/addons/product_list_price_from_pricelist/i18n/product_list_price_from_pricelist.pot
odoo/addons/product_list_price_from_pricelist/models/__init__.py
odoo/addons/product_list_price_from_pricelist/models/product_pricelist.py
odoo/addons/product_list_price_from_pricelist/models/res_company.py
odoo/addons/product_list_price_from_pricelist/models/res_config_settings.py
odoo/addons/product_list_price_from_pricelist/readme/CONFIGURE.md
odoo/addons/product_list_price_from_pricelist/readme/CONTRIBUTORS.md
odoo/addons/product_list_price_from_pricelist/readme/DESCRIPTION.md
odoo/addons/product_list_price_from_pricelist/readme/ROADMAP.md
odoo/addons/product_list_price_from_pricelist/readme/USAGE.md
odoo/addons/product_list_price_from_pricelist/static/description/icon.png
odoo/addons/product_list_price_from_pricelist/static/description/index.html
odoo/addons/product_list_price_from_pricelist/tests/__init__.py
odoo/addons/product_list_price_from_pricelist/tests/test_pricelist.py
odoo/addons/product_list_price_from_pricelist/views/res_config_settings_views.xml
odoo_addon_product_list_price_from_pricelist-18.0.1.0.0.2.dist-info/METADATA
odoo_addon_product_list_price_from_pricelist-18.0.1.0.0.2.dist-info/WHEEL
odoo_addon_product_list_price_from_pricelist-18.0.1.0.0.2.dist-info/top_level.txt
odoo_addon_product_list_price_from_pricelist-18.0.1.0.0.2.dist-info/RECORD
